{
  "time": { "useUTC": false },
  "chart": {
    "backgroundColor": "transparent",
    "spacing": 0,
    "spacingBottom": 5,
    "animation": false,
    "panning": false
  },
  "exporting": { "enabled": false },
  "navigator": { "enabled": false },
  "scrollbar": { "enabled": false },
  "credits": { "enabled": false },
  "rangeSelector": { "enabled": false },
  "title": { "enabled": false },
  "plotOptions": {
    "series": {
      "dataGrouping": {
        "enabled": false
      },
      "states": {
        "hover": {
          "enabled": false,
          "animation": 0,
          "halo": false
        }
      },
      "marker": {
        "states": {
          "hover": { "enabled": false, "radiusPlus": 0, "lineWidthPlus": 0 }
        }
      }
    },
    "line": { "marker": { "enabled": false } },
    "sma": { "marker": { "enabled": false } },
    "areaspline": {
      "pointPlacement": "onbetween",
      "showInLegend": false,
      "tooltip": {
        "valueDecimals": 2
      }
    },
    "candlestick": {
      "states": {
        "hover": { "halo": false, "brightness": 0, "lineWidthPlus": 0 }
      }
    },
    "scatter": {
      "tooltip": {
        "pointFormat": "{point.name}"
      }
    }
  },
  "tooltip": {
    "split": true,
    "shared": false,
    "hideDelay": 0,
    "borderWidth": 0,
    "shadow": false,
    "valueDecimals": 2,
    "followPointer": false,
    "padding": 4,
    "outside": true,
    "headerFormat": "{point.x:%H:%M:%S}",
    "style": { "fontFamily": "Roboto Condensed", "color": "white" }
  },
  "xAxis": {
    "tickWidth": 0,
    "lineColor": "transparent",
    "ordinal": false,
    "crosshair": {
      "width": 1,
      "dashStyle": "dash",
      "snap": false
    },
    "labels": {
      "y": 15
    }
  },
  "yAxis": [
    {
      "top": "0%",
      "height": "90%",
      "min": null,
      "max": null,
      "startOnTick": false,
      "alignTicks": false,
      "endOnTick": false,
      "gridLineWidth": 1,
      "minorGridLineWidth": 1,
      "tickPixelInterval": 16,
      "tickPosition": "outside",
      "showFirstLabel": false,
      "showLastLabel": false,
      "crosshair": {
        "width": 1,
        "dashStyle": "dash",
        "snap": false
      },
      "labels": {
        "align": "right",
        "x": -5,
        "y": -8
      }
    },
    {
      "visible": false,
      "top": "75%",
      "height": "25%"
    },
    {
      "visible": false,
      "top": "75%",
      "height": "25%"
    }
  ],
  "series": [
    {
      "id": "price",
      "type": "candlestick",
      "name": "BTCUSD",
      "data": [],
      "lineWidth": 1
    },
    {
      "id": "buys",
      "type": "column",
      "stacking": "stream",
      "name": "BUYS",
      "data": [],
      "yAxis": 1,
      "lineWidth": 0
    },
    {
      "id": "sells",
      "type": "column",
      "stacking": "stream",
      "name": "SELLS",
      "color": "rgba(233, 30, 99, 1)",
      "data": [],
      "yAxis": 1,
      "lineWidth": 0
    },
    {
      "stacking": "stream",
      "id": "liquidations",
      "type": "column",
      "name": "LIQUIDATIONS",
      "data": [],
      "fillColor": {
        "linearGradient": { "x1": 0, "y1": 0, "x2": 0, "y2": 1 },
        "stops": [[0, "rgba(140, 97, 245, .5)"], [1, "rgba(140, 97, 245, .4)"]]
      },
      "yAxis": 1
    },
    {
      "type": "ema",
      "name": "SELLS ema (14)",
      "id": "sells",
      "params": { "period": 14 },
      "linkedTo": "sells",
      "marker": { "enabled": false },
      "yAxis": 2
    },
    {
      "type": "ema",
      "name": "BUYS ema (14)",
      "params": { "period": 14 },
      "linkedTo": "buys",
      "marker": { "enabled": false },
      "yAxis": 2
    },
    {
      "type": "sma",
      "name": "SMA (14)",
      "params": { "period": 14 },
      "linkedTo": "price",
      "marker": { "enabled": false }
    }
  ],
  "theme": {
    "labels": "rgba(255, 255, 255, .2)",
    "up": "rgb(195, 168, 122)",
    "down": "rgb(193, 64, 71)",
    "buys": "rgb(117,193,165)",
    "sells": "rgb(205,103,108)",
    "liquidations": "rgba(140, 97, 245, 1)",
    "priceMA": "rgba(255, 255, 255, .33)",
    "buysMA": "rgb(201,176,135)",
    "sellsMA": "rgb(193, 64, 71)",
    "tooltipBackground": "rgba(0, 0, 0, .5)",
    "tooltipColor": "rgba(255, 255, 255, 1)",
    "crosshair": "rgba(255, 255, 255, .4)",
    "gridline": "rgba(255, 255, 255, .1)"
  }
}
